Workbook

Sheet Quick Start
A1: Account & Trigger Tracker
B2: Part of the Commercial Cleaning Client Acquisition OS
B5: What this is
B6: A working tracker for finding commercial accounts worth pursuing, the person who signs, and the
B7: reason to contact them now. It replaces the notebook, the sticky notes and the three spreadsheets.
B9: Start here — about 30 minutes
A10: 1 | B10: Open the Trigger Library tab. Read it once. It is the eleven public signals worth acting on.
A11: 2 | B11: Open Account Tracker. Delete the four example rows (they are marked). Add ten real accounts
B12: from your own city. Ten is enough to learn the system.
A13: 3 | B13: Score each one. The four score columns are dropdowns; Total and Band calculate themselves.
A14: 4 | B14: Work anything scoring 16+ first. Below 8, stop — it will cost more than it returns.
A15: 5 | B15: For each account you keep, add the person who signs in Contact Tracker.
A16: 6 | B16: Find the trigger. Log it in Trigger Tracker with a date and where you found it.
A17: 7 | B17: Pick the matching template in Outreach Templates. Send it.
A18: 8 | B18: Log the send in Follow-up Tracker so nothing goes quiet.
B20: The one rule that matters
B21: Every account you are actively working needs an owner, a next action, and a date.
B22: No next action means it is not in your pipeline. It is a name on a list.
B24: The tabs
B25: Quick Start — this page
B26: Instructions — how each tab works, in detail
B27: Account Tracker — the main sheet. One row per building
B28: Contact Tracker — one row per person
B29: Trigger Tracker — the dated reason you are contacting each account
B30: Campaign Tracker — which outreach batch went to whom
B31: Follow-up Tracker — every touch, so nothing is missed or repeated
B32: Pipeline — a live view of where everything stands
... B40: Everything else is a guess, and buyers can tell.

Sheet Lists
A1: Property Management | B1: Target | C1: 0 | D1: 0 | E1: 0 | F1: Owner | G1: New location | H1: Verified | I1: Practice Manager | J1: Email | K1: Sent | L1: Price | M1: Not serviceable - area
A2: Office / Professional | B2: Researching | C2: 1 | D2: 1 | E2: 1 | F2: Sales | G2: New facility / occupancy | H2: Pattern guess | I2: Office Manager | J2: Phone | K2: Replied - positive | L2: Incumbent retained | M2: Not serviceable - scope
A3: Medical / Dental | B3: Contacted | C3: 2 | D3: 2 | E3: 2 | F3: Admin | G3: Move / relocation | H3: Unverified | I3: Facilities Manager | J3: In person | K3: Replied - not now | L3: Awarded competitor | M3: Too small
A4: Industrial | B4: Follow-up | C4: 3 | D4: 3 | G4: Property management change | H4: Invalid | I4: Property Manager | J4: LinkedIn | K4: Replied - has provider | L4: No decision | M4: Chain decides centrally
A5: Retail | B5: Conversation | C5: 4 | G5: Facilities or ops hiring | H5: Unknown | I5: Operations Manager | K5: Replied - wrong person | L5: Scope mismatch | M5: No reachable contact
A6: School / Daycare | B6: Walkthrough Scheduled | C6: 5 | G6: Renovation / reopening | I6: General Manager | K6: Replied - no | L6: Timing | M6: Opted out
A7: Fitness | B7: Walkthrough Complete | G7: Acquisition | I7: Director | K7: Opted out | L7: Lost contact | M7: Duplicate
A8: Place of Worship | B8: Proposal Sent | G8: Headcount growth | I8: Business Manager | K8: Bounced | L8: We declined | M8: Out of business
A9: Other | B9: Negotiation | G9: Funding / news | I9: Owner | K9: No reply | M9: Not a fit
B10: Won | G10: Other | I10: Other
B11: Lost | I11: Unknown
B12: Nurture
B13: Disqualified

Sheet Account Tracker
A1: Account Tracker
A2: One row per building. Score it, stage it, and give it a next action with a date.
A3: Account ID | B3: Company | C3: Website | D3: City | E3: State | F3: Segment | G3: Est. sq ft | H3: Est. monthly value | I3: Fit 0-5 | J3: Value 0-5 | K3: Trigger 0-5 | L3: Access 0-3 | M3: Service 0-2 | N3: TOTAL | O3: Band | P3: Stage | Q3: Owner | R3: Next action | S3: Next action date | T3: Days overdue | U3: Last contact | V3: Source | W3: Date found | X3: Duplicate? | Y3: Notes
A4: ACC-001 | B4: (example) Northgate Dental | C4: northgate-example.com | D4: Irving | E4: TX | F4: Medical / Dental | G4: 4200 | I4: 4 | J4: 3 | K4: 5 | L4: 2 | M4: 2 | N4: =IF(COUNT(I4:M4)=5,SUM(I4:M4),"") | O4: =IF(N4="","",IF(N4>=16,"Priority",IF(N4>=12,"Active",IF(N4>=8,"Nurture / research","Park")))) | P4: Contacted | Q4: Owner | R4: Send follow-up email 2 | S4: =TODAY()+2 | T4: =IF(OR(S4="",P4="Won",P4="Lost",P4="Disqualified"),"",IF(TODAY()>S4,TODAY()-S4,0)) | V4: Maps + site | W4: =TODAY()-14 | X4: =IF(C4="","",IF(COUNTIF($C$4:$C$403,C4)>1,"DUPLICATE","")) | Y4: Moved into new building. Practice manager named on site.
A5: ACC-002 | B5: (example) Cedar Ridge Offices | C5: cedarridge-example.com | D5: Plano | E5: TX | F5: Office / Professional | G5: 9000 | I5: 4 | J5: 4 | K5: 3 | L5: 3 | M5: 2 | N5: =IF(COUNT(I5:M5)=5,SUM(I5:M5),"") | O5: =IF(N5="","",IF(N5>=16,"Priority",IF(N5>=12,"Active",IF(N5>=8,"Nurture / research","Park")))) | P5: Researching | Q5: Owner | R5: Find office manager name | S5: =TODAY()+1 | T5: =IF(OR(S5="",P5="Won",P5="Lost",P5="Disqualified"),"",IF(TODAY()>S5,TODAY()-S5,0)) | V5: Maps | W5: =TODAY()-6 | X5: =IF(C5="","",IF(COUNTIF($C$4:$C$403,C5)>1,"DUPLICATE","")) | Y5: Two suites, one entrance. Needs a site check.
A6: ACC-003 | B6: (example) Foster Property Group | C6: fosterpg-example.com | D6: Dallas | E6: TX | F6: Property Management | I6: 5 | J6: 5 | K6: 5 | L6: 2 | M6: 2 | N6: =IF(COUNT(I6:M6)=5,SUM(I6:M6),"") | O6: =IF(N6="","",IF(N6>=16,"Priority",IF(N6>=12,"Active",IF(N6>=8,"Nurture / research","Park")))) | P6: Conversation | Q6: Owner | R6: Confirm walkthrough date in writing | S6: =TODAY() | T6: =IF(OR(S6="",P6="Won",P6="Lost",P6="Disqualified"),"",IF(TODAY()>S6,TODAY()-S6,0)) | U6: =TODAY()-3 | V6: Portfolio page | W6: =TODAY()-21 | X6: =IF(C6="","",IF(COUNTIF($C$4:$C$403,C6)>1,"DUPLICATE","")) | Y6: Took on a building on Elm. Portfolio potential, not one site.
A7: ACC-004 | B7: (example) Brightpath Daycare | C7: brightpath-example.com | D7: Frisco | E7: TX | F7: School / Daycare | G7: 3100 | I7: 3 | J7: 2 | K7: 1 | L7: 1 | M7: 2 | N7: =IF(COUNT(I7:M7)=5,SUM(I7:M7),"") | O7: =IF(N7="","",IF(N7>=16,"Priority",IF(N7>=12,"Active",IF(N7>=8,"Nurture / research","Park")))) | P7: Nurture | Q7: Owner | R7: Check back before term | S7: =TODAY()+45 | T7: =IF(OR(S7="",P7="Won",P7="Lost",P7="Disqualified"),"",IF(TODAY()>S7,TODAY()-S7,0)) | V7: Maps | W7: =TODAY()-30 | X7: =IF(C7="","",IF(COUNTIF($C$4:$C$403,C7)>1,"DUPLICATE","")) | Y7: Happy with current cleaner. Review before autumn term.
N8: =IF(COUNT(I8:M8)=5,SUM(I8:M8),"") | O8: =IF(N8="","",IF(N8>=16,"Priority",IF(N8>=12,"Active",IF(N8>=8,"Nurture / research","Park")))) | T8: =IF(OR(S8="",P8="Won",P8="Lost",P8="Disqualified"),"",IF(TODAY()>S8,TODAY()-S8,0)) | X8: =IF(C8="","",IF(COUNTIF($C$4:$C$403,C8)>1,"DUPLICATE",""))
N9: =IF(COUNT(I9:M9)=5,SUM(I9:M9),"") | O9: =IF(N9="","",IF(N9>=16,"Priority",IF(N9>=12,"Active",IF(N9>=8,"Nurture / research","Park")))) | T9: =IF(OR(S9="",P9="Won",P9="Lost",P9="Disqualified"),"",IF(TODAY()>S9,TODAY()-S9,0)) | X9: =IF(C9="","",IF(COUNTIF($C$4:$C$403,C9)>1,"DUPLICATE",""))
N10: =IF(COUNT(I10:M10)=5,SUM(I10:M10),"") | O10: =IF(N10="","",IF(N10>=16,"Priority",IF(N10>=12,"Active",IF(N10>=8,"Nurture / research","Park")))) | T10: =IF(OR(S10="",P10="Won",P10="Lost",P10="Disqualified"),"",IF(TODAY()>S10,TODAY()-S10,0)) | X10: =IF(C10="","",IF(COUNTIF($C$4:$C$403,C10)>1,"DUPLICATE",""))
N11: =IF(COUNT(I11:M11)=5,SUM(I11:M11),"") | O11: =IF(N11="","",IF(N11>=16,"Priority",IF(N11>=12,"Active",IF(N11>=8,"Nurture / research","Park")))) | T11: =IF(OR(S11="",P11="Won",P11="Lost",P11="Disqualified"),"",IF(TODAY()>S11,TODAY()-S11,0)) | X11: =IF(C11="","",IF(COUNTIF($C$4:$C$403,C11)>1,"DUPLICATE",""))
N12: =IF(COUNT(I12:M12)=5,SUM(I12:M12),"") | O12: =IF(N12="","",IF(N12>=16,"Priority",IF(N12>=12,"Active",IF(N12>=8,"Nurture / research","Park")))) | T12: =IF(OR(S12="",P12="Won",P12="Lost",P12="Disqualified"),"",IF(TODAY()>S12,TODAY()-S12,0)) | X12: =IF(C12="","",IF(COUNTIF($C$4:$C$403,C12)>1,"DUPLICATE",""))
N13: =IF(COUNT(I13:M13)=5,SUM(I13:M13),"") | O13: =IF(N13="","",IF(N13>=16,"Priority",IF(N13>=12,"Active",IF(N13>=8,"Nurture / research","Park")))) | T13: =IF(OR(S13="",P13="Won",P13="Lost",P13="Disqualified"),"",IF(TODAY()>S13,TODAY()-S13,0)) | X13: =IF(C13="","",IF(COUNTIF($C$4:$C$403,C13)>1,"DUPLICATE",""))
N14: =IF(COUNT(I14:M14)=5,SUM(I14:M14),"") | O14: =IF(N14="","",IF(N14>=16,"Priority",IF(N14>=12,"Active",IF(N14>=8,"Nurture / research","Park")))) | T14: =IF(OR(S14="",P14="Won",P14="Lost",P14="Disqualified"),"",IF(TODAY()>S14,TODAY()-S14,0)) | X14: =IF(C14="","",IF(COUNTIF($C$4:$C$403,C14)>1,"DUPLICATE",""))
N15: =IF(COUNT(I15:M15)=5,SUM(I15:M15),"") | O15: =IF(N15="","",IF(N15>=16,"Priority",IF(N15>=12,"Active",IF(N15>=8,"Nurture / research","Park")))) | T15: =IF(OR(S15="",P15="Won",P15="Lost",P15="Disqualified"),"",IF(TODAY()>S15,TODAY()-S15,0)) | X15: =IF(C15="","",IF(COUNTIF($C$4:$C$403,C15)>1,"DUPLICATE",""))
N16: =IF(COUNT(I16:M16)=5,SUM(I16:M16),"") | O16: =IF(N16="","",IF(N16>=16,"Priority",IF(N16>=12,"Active",IF(N16>=8,"Nurture / research","Park")))) | T16: =IF(OR(S16="",P16="Won",P16="Lost",P16="Disqualified"),"",IF(TODAY()>S16,TODAY()-S16,0)) | X16: =IF(C16="","",IF(COUNTIF($C$4:$C$403,C16)>1,"DUPLICATE",""))
N17: =IF(COUNT(I17:M17)=5,SUM(I17:M17),"") | O17: =IF(N17="","",IF(N17>=16,"Priority",IF(N17>=12,"Active",IF(N17>=8,"Nurture / research","Park")))) | T17: =IF(OR(S17="",P17="Won",P17="Lost",P17="Disqualified"),"",IF(TODAY()>S17,TODAY()-S17,0)) | X17: =IF(C17="","",IF(COUNTIF($C$4:$C$403,C17)>1,"DUPLICATE",""))
N18: =IF(COUNT(I18:M18)=5,SUM(I18:M18),"") | O18: =IF(N18="","",IF(N18>=16,"Priority",IF(N18>=12,"Active",IF(N18>=8,"Nurture / research","Park")))) | T18: =IF(OR(S18="",P18="Won",P18="Lost",P18="Disqualified"),"",IF(TODAY()>S18,TODAY()-S18,0)) | X18: =IF(C18="","",IF(COUNTIF($C$4:$C$403,C18)>1,"DUPLICATE",""))
N19: =IF(COUNT(I19:M19)=5,SUM(I19:M19),"") | O19: =IF(N19="","",IF(N19>=16,"Priority",IF(N19>=12,"Active",IF(N19>=8,"Nurture / research","Park")))) | T19: =IF(OR(S19="",P19="Won",P19="Lost",P19="Disqualified"),"",IF(TODAY()>S19,TODAY()-S19,0)) | X19: =IF(C19="","",IF(COUNTIF($C$4:$C$403,C19)>1,"DUPLICATE",""))
... N403: =IF(COUNT(I403:M403)=5,SUM(I403:M403),"") | O403: =IF(N403="","",IF(N403>=16,"Priority",IF(N403>=12,"Active",IF(N403>=8,"Nurture / research","Park")))) | T403: =IF(OR(S403="",P403="Won",P403="Lost",P403="Disqualified"),"",IF(TODAY()>S403,TODAY()-S403,0)) | X403: =IF(C403="","",IF(COUNTIF($C$4:$C$403,C403)>1,"DUPLICATE",""))

Sheet Contact Tracker
A1: Contact Tracker
A2: One row per person. A job title is not proof someone signs — confirm it.
A3: Contact ID | B3: Account ID | C3: Company | D3: First name | E3: Last name | F3: Role | G3: Role type | H3: Signs off? | I3: Email | J3: Email status | K3: Phone | L3: Line type | M3: Source | N3: Found on | O3: Opted out | P3: Notes
A4: CON-001 | B4: ACC-001 | C4: (example) Northgate Dental | D4: Dana | E4: Reyes | F4: Practice Manager | G4: Practice Manager | H4: Likely | I4: dana@northgate-example.com | J4: Verified | L4: Unknown | M4: Practice site - team page | N4: =TODAY()-13 | O4: No | P4: Named on the site. Not yet confirmed she signs.
A5: CON-002 | B5: ACC-003 | C5: (example) Foster Property Group | D5: Marcus | E5: Hale | F5: Property Manager | G5: Property Manager | H5: Confirmed | I5: m.hale@fosterpg-example.com | J5: Verified | L5: Landline | M5: Building listing | N5: =TODAY()-20 | O5: No | P5: Said on the call that he signs cleaning contracts.
A6: CON-003 | B6: ACC-002 | C6: (example) Cedar Ridge Offices | F6: Office Manager | G6: Office Manager | H6: Unknown | I6: info@cedarridge-example.com | J6: Verified | L6: Unknown | M6: Site contact page | N6: =TODAY()-6 | O6: No | P6: Generic inbox only. Write it to be forwarded.

Sheet Trigger Tracker
A1: Trigger Tracker
A2: The dated, public reason you are contacting this account. No date and no source means no trigger.
A3: Trigger ID | B3: Account ID | C3: Company | D3: Trigger type | E3: Tier | F3: Score | G3: What you observed (exact) | H3: Where you found it | I3: Date it happened | J3: Days old | K3: Window (days) | L3: Still fresh?
A4: TRG-001 | B4: ACC-001 | C4: (example) Northgate Dental | D4: Move / relocation | E4: =IF(D4="","",IFERROR(VLOOKUP(D4,'Trigger Library'!$B$4:$E$14,2,FALSE),"")) | F4: =IF(OR(D4="",H4="",I4=""),0,IFERROR(VLOOKUP(D4,'Trigger Library'!$B$4:$E$14,3,FALSE),0)) | G4: Listing address changed to 5910 N MacArthur Blvd | H4: Google Business Profile | I4: =TODAY()-26 | J4: =IF(I4="","",TODAY()-I4) | K4: =IF(D4="","",IFERROR(VLOOKUP(D4,'Trigger Library'!$B$4:$E$14,4,FALSE),"")) | L4: =IF(OR(J4="",K4=""),"",IF(J4<=K4,"Fresh","Expired"))
A5: TRG-002 | B5: ACC-003 | C5: (example) Foster Property Group | D5: Property management change | E5: =IF(D5="","",IFERROR(VLOOKUP(D5,'Trigger Library'!$B$4:$E$14,2,FALSE),"")) | F5: =IF(OR(D5="",H5="",I5=""),0,IFERROR(VLOOKUP(D5,'Trigger Library'!$B$4:$E$14,3,FALSE),0)) | G5: Elm Street building added to their portfolio page | H5: Company website - portfolio | I5: =TODAY()-34 | J5: =IF(I5="","",TODAY()-I5) | K5: =IF(D5="","",IFERROR(VLOOKUP(D5,'Trigger Library'!$B$4:$E$14,4,FALSE),"")) | L5: =IF(OR(J5="",K5=""),"",IF(J5<=K5,"Fresh","Expired"))
A6: TRG-003 | B6: ACC-002 | C6: (example) Cedar Ridge Offices | D6: Facilities or ops hiring | E6: =IF(D6="","",IFERROR(VLOOKUP(D6,'Trigger Library'!$B$4:$E$14,2,FALSE),"")) | F6: =IF(OR(D6="",H6="",I6=""),0,IFERROR(VLOOKUP(D6,'Trigger Library'!$B$4:$E$14,3,FALSE),0)) | G6: Job post: "Office Manager", published 2 weeks ago | H6: Indeed | I6: =TODAY()-14 | J6: =IF(I6="","",TODAY()-I6) | K6: =IF(D6="","",IFERROR(VLOOKUP(D6,'Trigger Library'!$B$4:$E$14,4,FALSE),"")) | L6: =IF(OR(J6="",K6=""),"",IF(J6<=K6,"Fresh","Expired"))
E7: =IF(D7="","",IFERROR(VLOOKUP(D7,'Trigger Library'!$B$4:$E$14,2,FALSE),"")) | F7: =IF(OR(D7="",H7="",I7=""),0,IFERROR(VLOOKUP(D7,'Trigger Library'!$B$4:$E$14,3,FALSE),0)) | J7: =IF(I7="","",TODAY()-I7) | K7: =IF(D7="","",IFERROR(VLOOKUP(D7,'Trigger Library'!$B$4:$E$14,4,FALSE),"")) | L7: =IF(OR(J7="",K7=""),"",IF(J7<=K7,"Fresh","Expired"))
E8: =IF(D8="","",IFERROR(VLOOKUP(D8,'Trigger Library'!$B$4:$E$14,2,FALSE),"")) | F8: =IF(OR(D8="",H8="",I8=""),0,IFERROR(VLOOKUP(D8,'Trigger Library'!$B$4:$E$14,3,FALSE),0)) | J8: =IF(I8="","",TODAY()-I8) | K8: =IF(D8="","",IFERROR(VLOOKUP(D8,'Trigger Library'!$B$4:$E$14,4,FALSE),"")) | L8: =IF(OR(J8="",K8=""),"",IF(J8<=K8,"Fresh","Expired"))
E9: =IF(D9="","",IFERROR(VLOOKUP(D9,'Trigger Library'!$B$4:$E$14,2,FALSE),"")) | F9: =IF(OR(D9="",H9="",I9=""),0,IFERROR(VLOOKUP(D9,'Trigger Library'!$B$4:$E$14,3,FALSE),0)) | J9: =IF(I9="","",TODAY()-I9) | K9: =IF(D9="","",IFERROR(VLOOKUP(D9,'Trigger Library'!$B$4:$E$14,4,FALSE),"")) | L9: =IF(OR(J9="",K9=""),"",IF(J9<=K9,"Fresh","Expired"))
E10: =IF(D10="","",IFERROR(VLOOKUP(D10,'Trigger Library'!$B$4:$E$14,2,FALSE),"")) | F10: =IF(OR(D10="",H10="",I10=""),0,IFERROR(VLOOKUP(D10,'Trigger Library'!$B$4:$E$14,3,FALSE),0)) | J10: =IF(I10="","",TODAY()-I10) | K10: =IF(D10="","",IFERROR(VLOOKUP(D10,'Trigger Library'!$B$4:$E$14,4,FALSE),"")) | L10: =IF(OR(J10="",K10=""),"",IF(J10<=K10,"Fresh","Expired"))
E11: =IF(D11="","",IFERROR(VLOOKUP(D11,'Trigger Library'!$B$4:$E$14,2,FALSE),"")) | F11: =IF(OR(D11="",H11="",I11=""),0,IFERROR(VLOOKUP(D11,'Trigger Library'!$B$4:$E$14,3,FALSE),0)) | J11: =IF(I11="","",TODAY()-I11) | K11: =IF(D11="","",IFERROR(VLOOKUP(D11,'Trigger Library'!$B$4:$E$14,4,FALSE),"")) | L11: =IF(OR(J11="",K11=""),"",IF(J11<=K11,"Fresh","Expired"))
E12: =IF(D12="","",IFERROR(VLOOKUP(D12,'Trigger Library'!$B$4:$E$14,2,FALSE),"")) | F12: =IF(OR(D12="",H12="",I12=""),0,IFERROR(VLOOKUP(D12,'Trigger Library'!$B$4:$E$14,3,FALSE),0)) | J12: =IF(I12="","",TODAY()-I12) | K12: =IF(D12="","",IFERROR(VLOOKUP(D12,'Trigger Library'!$B$4:$E$14,4,FALSE),"")) | L12: =IF(OR(J12="",K12=""),"",IF(J12<=K12,"Fresh","Expired"))
E13: =IF(D13="","",IFERROR(VLOOKUP(D13,'Trigger Library'!$B$4:$E$14,2,FALSE),"")) | F13: =IF(OR(D13="",H13="",I13=""),0,IFERROR(VLOOKUP(D13,'Trigger Library'!$B$4:$E$14,3,FALSE),0)) | J13: =IF(I13="","",TODAY()-I13) | K13: =IF(D13="","",IFERROR(VLOOKUP(D13,'Trigger Library'!$B$4:$E$14,4,FALSE),"")) | L13: =IF(OR(J13="",K13=""),"",IF(J13<=K13,"Fresh","Expired"))
E14: =IF(D14="","",IFERROR(VLOOKUP(D14,'Trigger Library'!$B$4:$E$14,2,FALSE),"")) | F14: =IF(OR(D14="",H14="",I14=""),0,IFERROR(VLOOKUP(D14,'Trigger Library'!$B$4:$E$14,3,FALSE),0)) | J14: =IF(I14="","",TODAY()-I14) | K14: =IF(D14="","",IFERROR(VLOOKUP(D14,'Trigger Library'!$B$4:$E$14,4,FALSE),"")) | L14: =IF(OR(J14="",K14=""),"",IF(J14<=K14,"Fresh","Expired"))
E15: =IF(D15="","",IFERROR(VLOOKUP(D15,'Trigger Library'!$B$4:$E$14,2,FALSE),"")) | F15: =IF(OR(D15="",H15="",I15=""),0,IFERROR(VLOOKUP(D15,'Trigger Library'!$B$4:$E$14,3,FALSE),0)) | J15: =IF(I15="","",TODAY()-I15) | K15: =IF(D15="","",IFERROR(VLOOKUP(D15,'Trigger Library'!$B$4:$E$14,4,FALSE),"")) | L15: =IF(OR(J15="",K15=""),"",IF(J15<=K15,"Fresh","Expired"))
E16: =IF(D16="","",IFERROR(VLOOKUP(D16,'Trigger Library'!$B$4:$E$14,2,FALSE),"")) | F16: =IF(OR(D16="",H16="",I16=""),0,IFERROR(VLOOKUP(D16,'Trigger Library'!$B$4:$E$14,3,FALSE),0)) | J16: =IF(I16="","",TODAY()-I16) | K16: =IF(D16="","",IFERROR(VLOOKUP(D16,'Trigger Library'!$B$4:$E$14,4,FALSE),"")) | L16: =IF(OR(J16="",K16=""),"",IF(J16<=K16,"Fresh","Expired"))
E17: =IF(D17="","",IFERROR(VLOOKUP(D17,'Trigger Library'!$B$4:$E$14,2,FALSE),"")) | F17: =IF(OR(D17="",H17="",I17=""),0,IFERROR(VLOOKUP(D17,'Trigger Library'!$B$4:$E$14,3,FALSE),0)) | J17: =IF(I17="","",TODAY()-I17) | K17: =IF(D17="","",IFERROR(VLOOKUP(D17,'Trigger Library'!$B$4:$E$14,4,FALSE),"")) | L17: =IF(OR(J17="",K17=""),"",IF(J17<=K17,"Fresh","Expired"))
E18: =IF(D18="","",IFERROR(VLOOKUP(D18,'Trigger Library'!$B$4:$E$14,2,FALSE),"")) | F18: =IF(OR(D18="",H18="",I18=""),0,IFERROR(VLOOKUP(D18,'Trigger Library'!$B$4:$E$14,3,FALSE),0)) | J18: =IF(I18="","",TODAY()-I18) | K18: =IF(D18="","",IFERROR(VLOOKUP(D18,'Trigger Library'!$B$4:$E$14,4,FALSE),"")) | L18: =IF(OR(J18="",K18=""),"",IF(J18<=K18,"Fresh","Expired"))
... E303: =IF(D303="","",IFERROR(VLOOKUP(D303,'Trigger Library'!$B$4:$E$14,2,FALSE),"")) | F303: =IF(OR(D303="",H303="",I303=""),0,IFERROR(VLOOKUP(D303,'Trigger Library'!$B$4:$E$14,3,FALSE),0)) | J303: =IF(I303="","",TODAY()-I303) | K303: =IF(D303="","",IFERROR(VLOOKUP(D303,'Trigger Library'!$B$4:$E$14,4,FALSE),"")) | L303: =IF(OR(J303="",K303=""),"",IF(J303<=K303,"Fresh","Expired"))

Sheet Campaign Tracker
A1: Campaign Tracker
A2: One row per batch you send. Keep batches small and single-purpose so you can tell what worked.
A3: Campaign ID | B3: Name | C3: Segment | D3: Trigger type | E3: Template used | F3: Date started | G3: Accounts | H3: Sent | I3: Replies | J3: Positive | K3: Reply % | L3: Positive % | M3: Notes
A4: CAM-001 | B4: (example) Irving medical - moves | C4: Medical / Dental | D4: Move / relocation | E4: Medical - new location | F4: =TODAY()-10 | G4: 18 | H4: 18 | I4: 2 | J4: 1 | K4: =IF(OR(H4="",H4=0),"",I4/H4) | L4: =IF(OR(H4="",H4=0),"",J4/H4) | M4: Small first batch. Learning what gets read.
K5: =IF(OR(H5="",H5=0),"",I5/H5) | L5: =IF(OR(H5="",H5=0),"",J5/H5)
K6: =IF(OR(H6="",H6=0),"",I6/H6) | L6: =IF(OR(H6="",H6=0),"",J6/H6)
K7: =IF(OR(H7="",H7=0),"",I7/H7) | L7: =IF(OR(H7="",H7=0),"",J7/H7)
K8: =IF(OR(H8="",H8=0),"",I8/H8) | L8: =IF(OR(H8="",H8=0),"",J8/H8)
K9: =IF(OR(H9="",H9=0),"",I9/H9) | L9: =IF(OR(H9="",H9=0),"",J9/H9)
K10: =IF(OR(H10="",H10=0),"",I10/H10) | L10: =IF(OR(H10="",H10=0),"",J10/H10)
K11: =IF(OR(H11="",H11=0),"",I11/H11) | L11: =IF(OR(H11="",H11=0),"",J11/H11)
K12: =IF(OR(H12="",H12=0),"",I12/H12) | L12: =IF(OR(H12="",H12=0),"",J12/H12)
K13: =IF(OR(H13="",H13=0),"",I13/H13) | L13: =IF(OR(H13="",H13=0),"",J13/H13)
K14: =IF(OR(H14="",H14=0),"",I14/H14) | L14: =IF(OR(H14="",H14=0),"",J14/H14)
K15: =IF(OR(H15="",H15=0),"",I15/H15) | L15: =IF(OR(H15="",H15=0),"",J15/H15)
K16: =IF(OR(H16="",H16=0),"",I16/H16) | L16: =IF(OR(H16="",H16=0),"",J16/H16)
... K103: =IF(OR(H103="",H103=0),"",I103/H103) | L103: =IF(OR(H103="",H103=0),"",J103/H103)

Sheet Follow-up Tracker
A1: Follow-up Tracker
A2: Every touch, logged. This is what stops an account going quiet, and stops you sending a sixth email.
A3: Date | B3: Account ID | C3: Company | D3: Contact | E3: Channel | F3: Step | G3: What you sent / said | H3: Outcome | I3: Next touch due | J3: Overdue? | K3: Notes
A4: =TODAY()-14 | B4: ACC-001 | C4: (example) Northgate Dental | D4: Dana Reyes | E4: Email | F4: 1 | G4: First email - referenced the move to MacArthur | H4: No reply | I4: =TODAY()-10 | J4: =IF(OR(I4="",H4="Opted out",H4="Replied - no"),"",IF(TODAY()>I4,"OVERDUE",""))
A5: =TODAY()-10 | B5: ACC-001 | C5: (example) Northgate Dental | D5: Dana Reyes | E5: Email | F5: 2 | G5: Follow-up - documentation point | H5: No reply | I5: =TODAY()-3 | J5: =IF(OR(I5="",H5="Opted out",H5="Replied - no"),"",IF(TODAY()>I5,"OVERDUE",""))
A6: =TODAY()-3 | B6: ACC-003 | C6: (example) Foster Property Group | D6: Marcus Hale | E6: Phone | F6: 3 | G6: Call - agreed to a walkthrough | H6: Replied - positive | I6: =TODAY() | J6: =IF(OR(I6="",H6="Opted out",H6="Replied - no"),"",IF(TODAY()>I6,"OVERDUE","")) | K6: Confirm date in writing.
J7: =IF(OR(I7="",H7="Opted out",H7="Replied - no"),"",IF(TODAY()>I7,"OVERDUE",""))
J8: =IF(OR(I8="",H8="Opted out",H8="Replied - no"),"",IF(TODAY()>I8,"OVERDUE",""))
J9: =IF(OR(I9="",H9="Opted out",H9="Replied - no"),"",IF(TODAY()>I9,"OVERDUE",""))
J10: =IF(OR(I10="",H10="Opted out",H10="Replied - no"),"",IF(TODAY()>I10,"OVERDUE",""))
J11: =IF(OR(I11="",H11="Opted out",H11="Replied - no"),"",IF(TODAY()>I11,"OVERDUE",""))
J12: =IF(OR(I12="",H12="Opted out",H12="Replied - no"),"",IF(TODAY()>I12,"OVERDUE",""))
J13: =IF(OR(I13="",H13="Opted out",H13="Replied - no"),"",IF(TODAY()>I13,"OVERDUE",""))
J14: =IF(OR(I14="",H14="Opted out",H14="Replied - no"),"",IF(TODAY()>I14,"OVERDUE",""))
J15: =IF(OR(I15="",H15="Opted out",H15="Replied - no"),"",IF(TODAY()>I15,"OVERDUE",""))
J16: =IF(OR(I16="",H16="Opted out",H16="Replied - no"),"",IF(TODAY()>I16,"OVERDUE",""))
J17: =IF(OR(I17="",H17="Opted out",H17="Replied - no"),"",IF(TODAY()>I17,"OVERDUE",""))
J18: =IF(OR(I18="",H18="Opted out",H18="Replied - no"),"",IF(TODAY()>I18,"OVERDUE",""))
... J503: =IF(OR(I503="",H503="Opted out",H503="Replied - no"),"",IF(TODAY()>I503,"OVERDUE",""))

Sheet Pipeline
A1: Pipeline
A2: A live view. Nothing is typed here — it reads from Account Tracker.
A3: By stage | F3: By band | I3: Health checks — all should read 0
A4: Stage | B4: Accounts | C4: Est. monthly value | D4: Overdue next actions | F4: Band | G4: Accounts | I4: Check | J4: Count
A5: Target | B5: =COUNTIF('Account Tracker'!$P$4:$P$403,A5) | C5: =SUMIF('Account Tracker'!$P$4:$P$403,A5,'Account Tracker'!$H$4:$H$403) | D5: =COUNTIFS('Account Tracker'!$P$4:$P$403,A5,'Account Tracker'!$T$4:$T$403,">0") | F5: Priority | G5: =COUNTIF('Account Tracker'!$O$4:$O$403,F5) | I5: Active accounts with no next action | J5: =COUNTIFS('Account Tracker'!$P$4:$P$403,"<>",'Account Tracker'!$R$4:$R$403,"")-COUNTIF('Account Tracker'!$P$4:$P$403,"Won")-COUNTIF('Account Tracker'!$P$4:$P$403,"Lost")-COUNTIF('Account Tracker'!$P$4:$P$403,"Disqualified")
A6: Researching | B6: =COUNTIF('Account Tracker'!$P$4:$P$403,A6) | C6: =SUMIF('Account Tracker'!$P$4:$P$403,A6,'Account Tracker'!$H$4:$H$403) | D6: =COUNTIFS('Account Tracker'!$P$4:$P$403,A6,'Account Tracker'!$T$4:$T$403,">0") | F6: Active | G6: =COUNTIF('Account Tracker'!$O$4:$O$403,F6) | I6: Overdue next actions | J6: =COUNTIF('Account Tracker'!$T$4:$T$403,">0")
A7: Contacted | B7: =COUNTIF('Account Tracker'!$P$4:$P$403,A7) | C7: =SUMIF('Account Tracker'!$P$4:$P$403,A7,'Account Tracker'!$H$4:$H$403) | D7: =COUNTIFS('Account Tracker'!$P$4:$P$403,A7,'Account Tracker'!$T$4:$T$403,">0") | F7: Nurture / research | G7: =COUNTIF('Account Tracker'!$O$4:$O$403,F7) | I7: Duplicate websites | J7: =COUNTIF('Account Tracker'!$X$4:$X$403,"DUPLICATE")
A8: Follow-up | B8: =COUNTIF('Account Tracker'!$P$4:$P$403,A8) | C8: =SUMIF('Account Tracker'!$P$4:$P$403,A8,'Account Tracker'!$H$4:$H$403) | D8: =COUNTIFS('Account Tracker'!$P$4:$P$403,A8,'Account Tracker'!$T$4:$T$403,">0") | F8: Park | G8: =COUNTIF('Account Tracker'!$O$4:$O$403,F8) | I8: Expired triggers still logged | J8: =COUNTIF('Trigger Tracker'!$L$4:$L$303,"Expired")
A9: Conversation | B9: =COUNTIF('Account Tracker'!$P$4:$P$403,A9) | C9: =SUMIF('Account Tracker'!$P$4:$P$403,A9,'Account Tracker'!$H$4:$H$403) | D9: =COUNTIFS('Account Tracker'!$P$4:$P$403,A9,'Account Tracker'!$T$4:$T$403,">0") | I9: Triggers missing a source or date | J9: =SUMPRODUCT(('Trigger Tracker'!$G$4:$G$303<>"")*(('Trigger Tracker'!$H$4:$H$303="")+('Trigger Tracker'!$I$4:$I$303="")>0))
A10: Walkthrough Scheduled | B10: =COUNTIF('Account Tracker'!$P$4:$P$403,A10) | C10: =SUMIF('Account Tracker'!$P$4:$P$403,A10,'Account Tracker'!$H$4:$H$403) | D10: =COUNTIFS('Account Tracker'!$P$4:$P$403,A10,'Account Tracker'!$T$4:$T$403,">0") | I10: Overdue follow-ups | J10: =COUNTIF('Follow-up Tracker'!$J$4:$J$503,"OVERDUE")
A11: Walkthrough Complete | B11: =COUNTIF('Account Tracker'!$P$4:$P$403,A11) | C11: =SUMIF('Account Tracker'!$P$4:$P$403,A11,'Account Tracker'!$H$4:$H$403) | D11: =COUNTIFS('Account Tracker'!$P$4:$P$403,A11,'Account Tracker'!$T$4:$T$403,">0") | I11: Contacts marked opted out | J11: =COUNTIF('Contact Tracker'!$O$4:$O$303,"Yes")
A12: Proposal Sent | B12: =COUNTIF('Account Tracker'!$P$4:$P$403,A12) | C12: =SUMIF('Account Tracker'!$P$4:$P$403,A12,'Account Tracker'!$H$4:$H$403) | D12: =COUNTIFS('Account Tracker'!$P$4:$P$403,A12,'Account Tracker'!$T$4:$T$403,">0")
A13: Negotiation | B13: =COUNTIF('Account Tracker'!$P$4:$P$403,A13) | C13: =SUMIF('Account Tracker'!$P$4:$P$403,A13,'Account Tracker'!$H$4:$H$403) | D13: =COUNTIFS('Account Tracker'!$P$4:$P$403,A13,'Account Tracker'!$T$4:$T$403,">0") | I13: Opted-out contacts are not a problem to fix — they are a record to keep.
A14: Won | B14: =COUNTIF('Account Tracker'!$P$4:$P$403,A14) | C14: =SUMIF('Account Tracker'!$P$4:$P$403,A14,'Account Tracker'!$H$4:$H$403) | D14: =COUNTIFS('Account Tracker'!$P$4:$P$403,A14,'Account Tracker'!$T$4:$T$403,">0")
A15: Lost | B15: =COUNTIF('Account Tracker'!$P$4:$P$403,A15) | C15: =SUMIF('Account Tracker'!$P$4:$P$403,A15,'Account Tracker'!$H$4:$H$403) | D15: =COUNTIFS('Account Tracker'!$P$4:$P$403,A15,'Account Tracker'!$T$4:$T$403,">0")
A16: Nurture | B16: =COUNTIF('Account Tracker'!$P$4:$P$403,A16) | C16: =SUMIF('Account Tracker'!$P$4:$P$403,A16,'Account Tracker'!$H$4:$H$403) | D16: =COUNTIFS('Account Tracker'!$P$4:$P$403,A16,'Account Tracker'!$T$4:$T$403,">0")
A17: Disqualified | B17: =COUNTIF('Account Tracker'!$P$4:$P$403,A17) | C17: =SUMIF('Account Tracker'!$P$4:$P$403,A17,'Account Tracker'!$H$4:$H$403) | D17: =COUNTIFS('Account Tracker'!$P$4:$P$403,A17,'Account Tracker'!$T$4:$T$403,">0")
A18: Active (Target → Negotiation) | B18: =SUM(B5:B13) | C18: =SUM(C5:C13) | D18: =SUM(D5:D13)

Sheet Weekly Metrics
A1: Weekly Metrics
A2: Fill one column each Friday. Ten minutes. The ratios calculate themselves.
A3: Week ending | B3: =TODAY()-70 | C3: =B3+7 | D3: =C3+7 | E3: =D3+7 | F3: =E3+7 | G3: =F3+7 | H3: =G3+7 | I3: =H3+7 | J3: =I3+7 | ... M3: =L3+7
A4: Qualified accounts added
A5: Verified decision makers
A6: Trigger-qualified accounts
A7: Outreach sent
A8: Follow-ups sent
A9: Replies
A10: Positive replies
A11: Conversations
A12: Walkthroughs
A13: Proposals sent
A14: Wins
A15: New recurring revenue won ($/mo)
A16: Reply rate | B16: =IF(OR(B6="",B6=0),"",B8/B6) | C16: =IF(OR(C6="",C6=0),"",C8/C6) | D16: =IF(OR(D6="",D6=0),"",D8/D6) | E16: =IF(OR(E6="",E6=0),"",E8/E6) | F16: =IF(OR(F6="",F6=0),"",F8/F6) | G16: =IF(OR(G6="",G6=0),"",G8/G6) | H16: =IF(OR(H6="",H6=0),"",H8/H6) | I16: =IF(OR(I6="",I6=0),"",I8/I6) | ... M16: =IF(OR(M6="",M6=0),"",M8/M6)
A17: Positive reply rate | B17: =IF(OR(B6="",B6=0),"",B9/B6) | C17: =IF(OR(C6="",C6=0),"",C9/C6) | D17: =IF(OR(D6="",D6=0),"",D9/D6) | E17: =IF(OR(E6="",E6=0),"",E9/E6) | F17: =IF(OR(F6="",F6=0),"",F9/F6) | G17: =IF(OR(G6="",G6=0),"",G9/G6) | H17: =IF(OR(H6="",H6=0),"",H9/H6) | I17: =IF(OR(I6="",I6=0),"",I9/I6) | ... M17: =IF(OR(M6="",M6=0),"",M9/M6)
A18: Positive → conversation | B18: =IF(OR(B9="",B9=0),"",B10/B9) | C18: =IF(OR(C9="",C9=0),"",C10/C9) | D18: =IF(OR(D9="",D9=0),"",D10/D9) | E18: =IF(OR(E9="",E9=0),"",E10/E9) | F18: =IF(OR(F9="",F9=0),"",F10/F9) | G18: =IF(OR(G9="",G9=0),"",G10/G9) | H18: =IF(OR(H9="",H9=0),"",H10/H9) | I18: =IF(OR(I9="",I9=0),"",I10/I9) | ... M18: =IF(OR(M9="",M9=0),"",M10/M9)
A19: Conversation → walkthrough | B19: =IF(OR(B10="",B10=0),"",B11/B10) | C19: =IF(OR(C10="",C10=0),"",C11/C10) | D19: =IF(OR(D10="",D10=0),"",D11/D10) | E19: =IF(OR(E10="",E10=0),"",E11/E10) | F19: =IF(OR(F10="",F10=0),"",F11/F10) | G19: =IF(OR(G10="",G10=0),"",G11/G10) | H19: =IF(OR(H10="",H10=0),"",H11/H10) | I19: =IF(OR(I10="",I10=0),"",I11/I10) | ... M19: =IF(OR(M10="",M10=0),"",M11/M10)
A20: Walkthrough → proposal | B20: =IF(OR(B11="",B11=0),"",B12/B11) | C20: =IF(OR(C11="",C11=0),"",C12/C11) | D20: =IF(OR(D11="",D11=0),"",D12/D11) | E20: =IF(OR(E11="",E11=0),"",E12/E11) | F20: =IF(OR(F11="",F11=0),"",F12/F11) | G20: =IF(OR(G11="",G11=0),"",G12/G11) | H20: =IF(OR(H11="",H11=0),"",H12/H11) | I20: =IF(OR(I11="",I11=0),"",I12/I11) | ... M20: =IF(OR(M11="",M11=0),"",M12/M11)
A21: Proposal → win | B21: =IF(OR(B12="",B12=0),"",B13/B12) | C21: =IF(OR(C12="",C12=0),"",C13/C12) | D21: =IF(OR(D12="",D12=0),"",D13/D12) | E21: =IF(OR(E12="",E12=0),"",E13/E12) | F21: =IF(OR(F12="",F12=0),"",F13/F12) | G21: =IF(OR(G12="",G12=0),"",G13/G12) | H21: =IF(OR(H12="",H12=0),"",H13/H12) | I21: =IF(OR(I12="",I12=0),"",I13/I12) | ... M21: =IF(OR(M12="",M12=0),"",M13/M12)
A23: How to read this
A24: Two numbers matter more than the rest: positive replies per outreach sent, and walkthrough → proposal.
A25: The first tells you whether your targeting and triggers are working. The second tells you whether your
A26: pricing and proposals are. A weak first number is not fixed by sending more; it is fixed by better accounts.
A28: Compare each week to your own previous weeks. Your baseline is the only benchmark that means anything —
A29: published industry figures are mostly produced by companies selling outreach software, and the spread
A30: between them is wide enough to justify almost any conclusion.
A32: Give it four weeks before you read anything into a ratio. Under about ten events, you are reading noise.
A34: If a number moves, ask what you changed. If you changed three things, you have learned nothing. Change one.

Sheet Trigger Library
A1: Trigger Library
A2: Eleven public signals. A trigger is an event, not a conclusion.
A3: # | B3: Trigger type | C3: Tier | D3: Score | E3: Window (days) | F3: Where to find it | G3: What you may say | H3: What you may NOT say
A4: 1 | B4: New location | C4: High | D4: 5 | E4: 120 | F4: New Google Business Profile under an existing brand; 'now open' notices; local business press | G4: Saw you opened the second location in August | H4: You'll need a cleaner there
A5: 2 | B5: New facility / occupancy | C5: High | D5: 5 | E5: 90 | F5: Occupancy and tenant-improvement permits on your county or city portal | G5: Saw the new building on Commerce cleared occupancy | H5: You don't have a cleaner yet
A6: 3 | B6: Move / relocation | C6: High | D6: 5 | E6: 90 | F6: Address change on their Google listing; 'we've moved' notices; business press | G6: Noticed you moved to Commerce Street | H6: Your old cleaner won't follow you
A7: 4 | B7: Property management change | C7: High | D7: 5 | E7: 90 | F7: Portfolio pages on management company sites; listing management changes | G7: Saw you picked up the Elm Street building | H7: The inherited vendor won't work out
A8: 5 | B8: Facilities or ops hiring | C8: Medium | D8: 3 | E8: 90 | F8: Indeed and LinkedIn: Facilities Manager, Office Manager, Operations Manager | G8: Saw you're hiring a facilities manager | H8: They'll want to replace their vendors
A9: 6 | B9: Renovation / reopening | C9: Medium | D9: 3 | E9: 60 | F9: Renovation permits; reopening notices; temporary closure on their listing | G9: Saw the renovation permit for the Oak Street site | H9: You'll need post-construction cleaning
A10: 7 | B10: Acquisition | C10: Medium | D10: 3 | E10: 120 | F10: Local business journals; press releases; state business registries | G10: Saw the acquisition announcement last month | H10: They'll be consolidating vendors
A11: 8 | B11: Headcount growth | C11: Low | D11: 1 | E11: 60 | F11: Several open roles at one address | G11: Looks like you're growing the team there | H11: More staff means you need us
A12: 9 | B12: Funding / news | C12: Low | D12: 1 | E12: 120 | F12: Local business journals | G12: Saw the announcement | H12: You have budget now
A13: 10 | B13: Other | C13: Low | D13: 1 | E13: 60 | F13: Anything public, dated, and specific | G13: State exactly what you observed | H13: Anything you inferred from it
A14: 11 | B14: Review mentions cleaning | C14: Low | D14: 1 | E14: 60 | F14: Public reviews mentioning cleanliness | G14: Nothing. Do not reference a review | H14: Anything at all — see the note below
B17: Why review mentions score 1, not 5
B18: A review saying the restrooms were dirty feels like the strongest signal on this page. It isn't.
B19: It does not tell you the business controls the cleaning contract, that the reviewer was an employee
B20: rather than a customer, that the problem is current, or that anyone is looking. It is an inference
B21: about dissatisfaction, not an observation of a purchase window.
B22: Use it to break a tie between two accounts that already have a real event. Never quote it to a
B23: prospect — it reads as surveillance, and it asserts something about their vendor you cannot support.
B25: Why the last column exists
B26: Everything in it is a conclusion. You saw a permit. You did not see their contract.
B27: State the event and offer to help. That is a legitimate reason to make contact, and it holds up
B28: when someone asks how you found them.
B30: Freshness
... B32: Work the freshest first. That is the whole advantage this gives you over a list.

Sheet Outreach Templates
A1: Outreach Templates
A2: Six sequences. Adapt the words; keep the structure.
A3: Every email follows four beats: what you observed → what you do → a conditional offer → an easy question.
A4: Replace [square brackets]. Delete anything that isn't true for you.
A6: Template | B6: Use when | C6: Email | D6: Subject | E6: Body
A7: Property management | B7: New building in their portfolio | C7: 1 | D7: the [street] building | E7: Hi [First name] — I noticed [company] recently added the [street] property to your portfolio. We handle recurring janitorial for commercial buildings around [area]. If you're reviewing cleaning coverage there, or inherited an arrangement you're still weighing up, I'd be glad to walk it and give you a scoped number. Would a short call this week be useful? — [Your name], [Your company]
C8: 2 | D8: re: the [street] building | E8: [First name] — following up briefly. Two things I'd want to know if I were you: how fast the vendor picks up the phone, and whether tenant complaints ever reach the owner. Happy to walk the building and put a scoped proposal together, whether or not anything changes today. Worth fifteen minutes?
C9: 3 | D9: closing the loop | E9: [First name] — I'll leave it there. If it's useful, tell me roughly when the current arrangement comes up for review and I'll check back then rather than filling your inbox. Either way, good luck with the new property.
A10: Medical - new location | B10: They moved or opened | C10: 1 | D10: the new [street] office | E10: Hi [First name] — I saw [practice] opened at [street] last month. Congratulations. We do recurring cleaning for medical and dental offices around [area] — after-hours, with documented restroom and treatment-room protocols. If cleaning for the new space is still being arranged, I'd be glad to walk it and put a scope and price together. Would Tuesday or Thursday suit for fifteen minutes?
C11: 2 | D11: re: the new [street] office | E11: [First name] — one thing worth asking whoever you use: whether they document what was cleaned, room by room. For a medical space it's useful to have that on file if anyone ever asks. Happy to show you what our reporting looks like, no obligation.
C12: 3 | D12: closing the loop | E12: [First name] — I'll stop here. If the timing isn't right, no problem at all. If it changes, the offer to walk the space stands. Either way, good luck with [the new space / the year].
A13: Office - move | B13: They moved or opened | C13: 1 | D13: your move to [street] | E13: Hi [First name] — noticed [company] moved into [street] recently. We handle nightly and weekly cleaning for offices around [area]. A move means sorting out a lot of vendors at once. If cleaning is still on that list, I can walk the space and have a scoped proposal to you in two days. Would a quick call this week help?
C14: 2 | D14: re: your move to [street] | E14: [First name] — briefly. If you're comparing providers, two questions worth asking each one: will it be the same crew every time, and what response time will they put in writing. Those are usually where the differences show up. Happy to walk the space either way.
C15: 3 | D15: closing the loop | E15: [First name] — I'll stop here. If the timing isn't right, no problem at all. If it changes, the offer to walk the space stands. Either way, good luck with [the new space / the year].
A16: Office - facilities hire | B16: They posted a facilities role | C16: 1 | D16: saw the facilities role | E16: Hi [First name] — saw [company] is hiring a facilities manager. We provide recurring commercial cleaning around [area]. When facilities becomes someone's actual job, vendor arrangements usually get reviewed at some point. No rush on my side. If it'd be useful to have a scoped quote on file for when that happens, I'm glad to walk the space. Worth a short call?
C17: 2 | D17: closing the loop | E17: [First name] — I'll stop here. If the timing isn't right, no problem at all. If it changes, the offer to walk the space stands. Either way, good luck with [the new space / the year].
A18: Industrial - new facility | B18: Occupancy or renovation | C18: 1 | D18: the [street] facility | E18: Hi [First name] — I saw the [street] facility recently cleared occupancy. We handle recurring cleaning for industrial and warehouse space around [area] — floors, restrooms, break areas, and post-construction cleanup where it's needed. If cleaning for the new space isn't settled, I'd be glad to walk it. Would next week work?
C19: 2 | D19: closing the loop | E19: [First name] — I'll stop here. If the timing isn't right, no problem at all. If it changes, the offer to walk the space stands. Either way, good luck with [the new space / the year].
A20: School / daycare | B20: New site, renovation, or before term | C20: 1 | D20: cleaning coverage for [school] | E20: Hi [First name] — I work with schools and childcare centres around [area] on recurring cleaning. I noticed [school] [what you observed]. Two things I'd expect matter here: the same crew each time, and staff who've been background-checked. Both are things I can put in writing. Happy to walk the site and put a scope together.
C21: 2 | D21: closing the loop | E21: [First name] — I'll stop here. If the timing isn't right, no problem at all. If it changes, the offer to walk the space stands. Either way, good luck with [the new space / the year].
A23: Rules that matter more than the wording
A24: Three emails, then stop. A fourth doesn't win the contract and costs you the chance to come back.
A25: Never say a prospect has no cleaner, is unhappy, or is shopping. You cannot know it.
A26: Use a conditional: 'if cleaning is still being arranged' — not 'you need a cleaner'.
A27: Plain text. No images, no logo block, no tracking pixel.
A28: Every email needs your business name, a real postal address, and a way to opt out.
A29: Honour any opt-out immediately and permanently, across email and phone. Never re-add.
A30: Never quote a review back to someone.
A31: If you change one thing at a time, you'll learn something. If you change five, you won't.

Sheet Instructions
A1: Instructions
A2: How each tab works, and the handful of rules that keep it honest.
B4: Account Tracker
B5: One row per building. Fill the left side by hand; the grey columns calculate.
B6: Score with the four dropdowns. TOTAL and Band appear automatically.
B7: Fit 0-5: is this the kind of building you should pursue? 0 means disqualify.
B8: Value 0-5: is it worth the effort if you win it? Estimate from square footage and frequency.
B9: Trigger 0-5: pull this from Trigger Tracker. No dated source means 0.
B10: Access 0-3: 3 only when you have a named person, the right role, and a verified email.
B11: Service 0-2: could you actually service it? 0 means disqualify.
B13: Bands: 16-20 work now. 12-15 work in order. 8-11 research or wait. Below 8, stop.
B14: Below 8 the account isn't worthless — it's just more expensive to chase than it returns.
B16: 'Days overdue' turns amber when a next action date has passed. 'Duplicate?' flags a website
B17: already in the sheet. The next-action column turns amber if an active account has none.
... B51: Everything else in this workbook exists to support that one habit.
